<?xml version="1.0"?>
<opencv_storage>
<stage7>
  <maxWeakCount>2</maxWeakCount>
  <stageThreshold>-4.4412622228264809e-03</stageThreshold>
  <weakClassifiers>
    <_>
      <internalNodes>
        0 -1 8360 336969759 -1323237117 51738 -738196992 -2146955245
        -1342111600 -2147184604 -74934240</internalNodes>
      <leafValues>
        -9.3577980995178223e-01 8.5294115543365479e-01</leafValues></_>
    <_>
      <internalNodes>
        0 -1 2832 1073911245 -1769668287 83894656 -821821436 -1610610526
        4718624 -2079817600 -939407359</internalNodes>
      <leafValues>
        -8.5738241672515869e-01 9.7556954622268677e-01</leafValues></_></weakClassifiers></stage7>
</opencv_storage>
